MANIFEST.in
README.rst
setup.py
collective/__init__.py
collective.transform.kml.egg-info/PKG-INFO
collective.transform.kml.egg-info/SOURCES.txt
collective.transform.kml.egg-info/dependency_links.txt
collective.transform.kml.egg-info/entry_points.txt
collective.transform.kml.egg-info/namespace_packages.txt
collective.transform.kml.egg-info/not-zip-safe
collective.transform.kml.egg-info/requires.txt
collective.transform.kml.egg-info/top_level.txt
collective/transform/__init__.py
collective/transform/kml/__init__.py
collective/transform/kml/configure.zcml
collective/transform/kml/kml_to_html.py
collective/transform/kml/setuphandlers.py
collective/transform/kml/tests.py
collective/transform/kml/version.txt
collective/transform/kml/profiles/default/collective.transform.kml.txt
collective/transform/kml/profiles/default/metadata.xml
docs/HISTORY.txt
docs/INSTALL.txt
docs/LICENSE.txt