Metadata-Version: 1.0
Name: collective.transform.kml
Version: 0.1
Summary: Transform KML to HTML
Home-page: https://github.com/collective/collective.transform.kml
Author: Christian Ledermann
Author-email: christian.ledermann@gmail.com
License: GPL
Platform: UNKNOWN
Classifier: Framework :: Plone
Classifier: Framework :: Plone :: 4.0
Classifier: Framework :: Plone :: 4.1
Classifier: Programming Language :: Python
Classifier: Topic :: Text Processing
